bkapi_client_core/__init__.py
bkapi_client_core/apigateway/__init__.py
bkapi_client_core/apigateway/client.py
bkapi_client_core/apigateway/django_helper.py
bkapi_client_core/auth.py
bkapi_client_core/base.py
bkapi_client_core/client.py
bkapi_client_core/config.py
bkapi_client_core/django_helper.py
bkapi_client_core/esb/__init__.py
bkapi_client_core/esb/client.py
bkapi_client_core/esb/django_helper.py
bkapi_client_core/exceptions.py
bkapi_client_core/prometheus.py
bkapi_client_core/property.py
bkapi_client_core/session.py
bkapi_client_core/utils.py
bkapi_client_core-1.2.0.dist-info/METADATA
bkapi_client_core-1.2.0.dist-info/WHEEL
bkapi_client_core-1.2.0.dist-info/RECORD
