Metadata-Version: 2.1
Name: bkapi-client-core
Version: 1.2.0
Summary: A toolkit for buiding blueking API clients.
License: MIT
Author: blueking
Author-email: blueking@tencent.com
Requires-Python: >=2.7, !=3.0.*, !=3.1.*, !=3.2.*, !=3.3.*, !=3.4.*, !=3.5.*
Classifier: License :: OSI Approved :: MIT License
Classifier: Programming Language :: Python :: 2
Classifier: Programming Language :: Python :: 2.7
Classifier: Programming Language :: Python :: 3
Classifier: Programming Language :: Python :: 3.6
Classifier: Programming Language :: Python :: 3.7
Classifier: Programming Language :: Python :: 3.8
Classifier: Programming Language :: Python :: 3.9
Classifier: Programming Language :: Python :: 3.10
Classifier: Programming Language :: Python :: 3.11
Provides-Extra: django
Provides-Extra: monitor
Requires-Dist: bkoauth (>=0.0.10) ; extra == "django"
Requires-Dist: curlify (>=2.0)
Requires-Dist: prometheus-client (>=0.9.0) ; extra == "django" or extra == "monitor"
Requires-Dist: requests (>=2.20)
Requires-Dist: six
Requires-Dist: typing (>=3.10.0,<4.0.0) ; python_version == "2.7"
Requires-Dist: typing-extensions (>=3.7.4)
